anchor_terminal/__init__.py
anchor_terminal/terminal.py
anchor_terminal-0.1.2.dist-info/LICENSE
anchor_terminal-0.1.2.dist-info/METADATA
anchor_terminal-0.1.2.dist-info/WHEEL
anchor_terminal-0.1.2.dist-info/entry_points.txt
anchor_terminal-0.1.2.dist-info/top_level.txt
anchor_terminal-0.1.2.dist-info/RECORD
