Metadata-Version: 2.1
Name: anchor-terminal
Version: 0.1.2
Summary: A Docker workflow tool
Author-email: Jesper Fjellin <jesperfjellin@gmail.com>
License: MIT
Requires-Python: >=3.8
License-File: LICENSE
